pymobyt/__init__.py
pymobyt/mobyt.py
python_mobyt-0.4.3.dist-info/METADATA
python_mobyt-0.4.3.dist-info/WHEEL
python_mobyt-0.4.3.dist-info/top_level.txt
python_mobyt-0.4.3.dist-info/RECORD
