Metadata-Version: 2.1
Name: python-mobyt
Version: 0.4.3
Summary: Mobyt API Client
Home-page: https://github.com/metadonors/python-mobyt
Author: Metadonors
Author-email: fabrizio.arzeni@metadonors.it
License: MIT
Platform: UNKNOWN
Requires-Dist: requests
